symmetry/__init__.py
symmetry/api/__init__.py
symmetry/api/cluster.py
symmetry/api/events.py
symmetry/api/nodes.py
symmetry/api/routing.py
symmetry/api/service.py
symmetry/api/telemetry.py
symmetry/cli/__init__.py
symmetry/cli/clusterd.py
symmetry/cli/rtable.py
symmetry/cli/symmetry.py
symmetry/cli/telemc.py
symmetry/cli/websocket.py
symmetry/clusterd/__init__.py
symmetry/clusterd/clusterd.py
symmetry/clusterd/info.py
symmetry/clusterd/monitor.py
symmetry/clusterd/noded.py
symmetry/clusterd/policyd.py
symmetry/clusterd/policies/__init__.py
symmetry/clusterd/policies/balancing.py
symmetry/common/__init__.py
symmetry/common/cluster.py
symmetry/common/config.py
symmetry/common/scheduler.py
symmetry/common/shell.py
symmetry/common/ssh.py
symmetry/common/typing.py
symmetry/gateway/__init__.py
symmetry/gateway/proxy.py
symmetry/gateway/router.py
symmetry/nrg/__init__.py
symmetry/nrg/docker.py
symmetry/nrg/manager.py
symmetry/nrg/metadata.py
symmetry/nrg/ports.py
symmetry/nrg/proxy.py
symmetry/nrg/web.py
symmetry/routing/__init__.py
symmetry/routing/shell.py
symmetry/routing/table.py
symmetry/telemetry/__init__.py
symmetry/telemetry/client.py
symmetry/telemetry/recorder.py
symmetry/webapp/__init__.py
symmetry/webapp/app.py
symmetry/webapp/client.py
symmetry/webapp/gunicorn.conf.py
symmetry/webapp/wsgi.py
symmetry/webapp/ws/__init__.py
symmetry/webapp/ws/websocket.py
tests/__init__.py
tests/test_balancer.py
tests/test_cluster.py
tests/test_config.py
tests/test_port_allocator.py
tests/test_router.py
tests/test_routing_table.py
tests/test_scheduler.py
tests/test_shell.py
tests/test_typing.py
tests/testutils.py
tests/clusterd/__init__.py
tests/clusterd/test_balancing.py
tests/clusterd/test_clusterd.py
tests/clusterd/test_monitor.py
tests/webapp/__init__.py
tests/webapp/test_app.py
mc2_symmetry-0.6.0.dist-info/METADATA
mc2_symmetry-0.6.0.dist-info/WHEEL
mc2_symmetry-0.6.0.dist-info/entry_points.txt
mc2_symmetry-0.6.0.dist-info/top_level.txt
mc2_symmetry-0.6.0.dist-info/RECORD
