Metadata-Version: 2.1
Name: mc2-symmetry
Version: 0.6.0
Summary: Symmetry - A cluster management system for micro-clusters
Home-page: https://git.dsg.tuwien.ac.at/mc2/symmetry
Author: Thomas Rausch
Author-email: t.rausch@dsg.tuwien.ac.at
License: UNKNOWN
Platform: UNKNOWN
Classifier: Programming Language :: Python :: 3
Classifier: Operating System :: OS Independent
Requires-Dist: telemc (>=0.3.0)
Requires-Dist: falcon (==2.0.0)
Requires-Dist: falcon-cors
Requires-Dist: falcon-multipart (>=0.2.0)
Requires-Dist: gunicorn (==19.9.0)
Requires-Dist: paramiko (==2.6.0)
Requires-Dist: wakeonlan (==1.1.6)
Requires-Dist: redis (==3.2.1)
Requires-Dist: pyserial (==3.4)
Requires-Dist: websockets (==7.0)
Requires-Dist: aioredis (==1.2.0)
Requires-Dist: pyyaml (==5.1)
Requires-Dist: requests (==2.20.1)
Requires-Dist: click (>=7.0)
Requires-Dist: Jinja2 (>=2.10.1)
Requires-Dist: docker (==4.0.2)
Requires-Dist: pymq (>=0.3.0)
